gitWebhook/__init__.py
gitWebhook/abstractWebhook.py
gitWebhook/functionWebhook.py
gitWebhook/pullerWebhook.py
gitWebhook/webhook.py
gitAppWebhook-0.4.dist-info/METADATA
gitAppWebhook-0.4.dist-info/WHEEL
gitAppWebhook-0.4.dist-info/top_level.txt
gitAppWebhook-0.4.dist-info/RECORD
