Metadata-Version: 2.1
Name: gitAppWebhook
Version: 0.4
Summary: Flask blueprints for handling GitHub and GitLab webhooks
Author-email: TCA <tca.youtub@gmail.com>
Project-URL: Homepage, https://github.com/TCA166/gitWebhook
Classifier: Programming Language :: Python :: 3
Classifier: Operating System :: OS Independent
Requires-Python: >=3.8
Requires-Dist: flask
